{
    "Greetings": [1, 3, 17, 30, 31, 44, 45],
    "Apologetic": [25, 32, 33],
    "Thankful": [18, 38],
    "Angry/Irritated": [6, 7, 14, 21, 43],
    "Enthusiastic": [9, 26, 27, 50],
    "Approval": [8, 34, 37, 39],
    "Agreement": [35],
    "Disagreement": [],
    "Attack/Victory": [],
    "Retreat": [],
    "Suggestions": [11, 46, 48],
    "Reprimand": [13, 22, 41, 42, 47],
    "Generous/Helpful": [2],
    "Warnings": [4, 5, 19, 40],
    "Eager/Ready": [12, 20, 23, 24, 49],
    "Healing": [],
    "Disappointed": [15, 16],
    "Miscellaneous": [10, 36],
    "Farewells": [28, 29]
}